Metadata-Version: 2.4
Name: meu_investimento_aula3_fiap_gabriel
Version: 0.1
Summary: Uma biblioteca para cálculos de investimentos.
Home-page: https://github.com/
Author: Gabriel Siqueira de Lima
Author-email: gabrielsiqueira094@gmail.com
Classifier: Programming Language :: Python :: 3
Classifier: License :: OSI Approved :: MIT License
Classifier: Operating System :: OS Independent
Requires-Python: >=3.6
License-File: LICENSE
Dynamic: author
Dynamic: author-email
Dynamic: classifier
Dynamic: home-page
Dynamic: license-file
Dynamic: requires-python
Dynamic: summary
